paralg/__init__.py
paralg/helpers.py
paralg/experiments/__init__.py
paralg/experiments/logger.py
paralg/experiments/sorting.py
paralg/sorting/__init__.py
paralg/sorting/algorithms.py
tests/__init__.py
tests/test_helpers.py
tests/test_sorting.py
ParAlg-0.0.1.dist-info/LICENSE
ParAlg-0.0.1.dist-info/METADATA
ParAlg-0.0.1.dist-info/WHEEL
ParAlg-0.0.1.dist-info/top_level.txt
ParAlg-0.0.1.dist-info/RECORD
