Metadata-Version: 2.1
Name: ParAlg
Version: 0.0.1
Summary: Parallel Implementations of Algorithms
Home-page: https://github.com/Ashwin-op/paralg
Author: Ashwin
Author-email: bosshere2@gmail.com
License: UNKNOWN
Platform: UNKNOWN
Classifier: Programming Language :: Python :: 3
Classifier: License :: OSI Approved :: MIT License
Classifier: Operating System :: OS Independent
Requires-Python: >=3.7
